rtl/pc.v
module pc (
    input clk,
    input reset,
    output reg [31:0] pc_out
);

always @(posedge clk or posedge reset)
begin
    if(reset)
        pc_out <= 32'h00000000;
    else
        pc_out <= pc_out + 4;
end

endmodule

tb/pc_tb.v
`timescale 1ns/1ps

module pc_tb;

reg clk;
reg reset;

wire [31:0] pc_out;

pc uut (
    .clk(clk),
    .reset(reset),
    .pc_out(pc_out)
);

always #5 clk = ~clk;

initial
begin
    clk = 0;
    reset = 1;

    #10;
    reset = 0;

    #100;

    $finish;
end

initial
begin
    $monitor("Time=%0t Reset=%b PC=%d",
             $time, reset, pc_out);
end

initial
begin
    $dumpfile("pc.vcd");
    $dumpvars(0, pc_tb);
end

endmodule

pc.vcd
$date
	Wed Jun 17 23:40:28 2026
$end
$version
	Icarus Verilog
$end
$timescale
	1ps
$end
$scope module pc_tb $end
$var wire 32 ! pc_out [31:0] $end
$var reg 1 " clk $end
$var reg 1 # reset $end
$scope module uut $end
$var wire 1 " clk $end
$var wire 1 # reset $end
$var reg 32 $ pc_out [31:0] $end
$upscope $end
$upscope $end
$enddefinitions $end
#0
$dumpvars
b0 $
1#
0"
b0 !
$end
#5000
1"
#10000
0"
0#
#15000
b100 !
b100 $
1"
#20000
0"
#25000
b1000 !
b1000 $
1"
#30000
0"
#35000
b1100 !
b1100 $
1"
#40000
0"
#45000
b10000 !
b10000 $
1"
#50000
0"
#55000
b10100 !
b10100 $
1"
#60000
0"
#65000
b11000 !
b11000 $
1"
#70000
0"
#75000
b11100 !
b11100 $
1"
#80000
0"
#85000
b100000 !
b100000 $
1"
#90000
0"
#95000
b100100 !
b100100 $
1"
#100000
0"
#105000
b101000 !
b101000 $
1"
